masterpiece_yamlformat/__init__.py
masterpiece_yamlformat/py.typed
masterpiece_yamlformat/yamlformat.py
masterpiece_yamlformat-1.0.8.dist-info/licenses/LICENSE.rst
masterpiece_yamlformat-1.0.8.dist-info/METADATA
masterpiece_yamlformat-1.0.8.dist-info/WHEEL
masterpiece_yamlformat-1.0.8.dist-info/entry_points.txt
masterpiece_yamlformat-1.0.8.dist-info/top_level.txt
masterpiece_yamlformat-1.0.8.dist-info/RECORD
