Metadata-Version: 2.4
Name: masterpiece-yamlformat
Version: 1.0.8
Summary: Yaml serialization format for `masterpiece` applications
Author-email: J Meskanen <juham.api@gmail.com>
Maintainer-email: "J. Meskanen" <juham.api@gmail.com>
License-Expression: MIT
Project-URL: Homepage, https://gitlab.com/juham/masterpiece_yamlformat
Project-URL: Bug Reports, https://gitlab.com/juham/masterpiece
Project-URL: Source, https://gitlab.com/juham/masterpiece_yamlformat
Project-URL: Say Thanks!, http://meskanen.com
Keywords: yaml,masterpiece,format,serialization
Classifier: Development Status :: 4 - Beta
Classifier: Intended Audience :: Developers
Classifier: Topic :: Software Development
Classifier: Programming Language :: Python :: 3.8
Requires-Python: >=3.8
License-File: LICENSE.rst
Requires-Dist: masterpiece>=0.1.44
Requires-Dist: pytz>=2024.1
Requires-Dist: importlib-metadata
Requires-Dist: pyyaml>=6.0
Provides-Extra: dev
Requires-Dist: check-manifest; extra == "dev"
Dynamic: license-file
